nexis/__init__.py
nexis/__main__.py
nexis/__version__.py
nexis/config/__init__.py
nexis/config/config.py
nexis/config/constants.py
nexis/config/exceptions.py
nexis/config/parsers/mode.py
nexis/config/parsers/parser.py
nexis/config/parsers/parsers.py
nexis/config/parsers/url.py
nexis/config/parsers/version.py
nexis/console/__init__.py
nexis/console/command_loader.py
nexis/console/commands/command.py
nexis/console/commands/docs.py
nexis/console/entrypoint.py
nexis/exceptions.py
nexis/factory.py
nexis/logging/__init__.py
nexis/logging/formatter.py
nexis/logging/handler.py
nexis/nexis.py
nexis/py.typed
nexis/utils/__init__.py
nexis/utils/compat.py
nexis/version.py
nexis-0.2.0.dist-info/LICENSE
nexis-0.2.0.dist-info/METADATA
nexis-0.2.0.dist-info/WHEEL
nexis-0.2.0.dist-info/entry_points.txt
nexis-0.2.0.dist-info/RECORD
