Metadata-Version: 2.1
Name: nexis
Version: 0.2.0
Summary: NYP InfoSec Auth CLI
License: GPL-3.0
Keywords: nyp,nypinfosec,auth,client,cli
Author: Alex
Author-email: contact@ngjx.org
Requires-Python: >=3.9,<4.0
Classifier: Development Status :: 1 - Planning
Classifier: Intended Audience :: End Users/Desktop
Classifier: License :: OSI Approved :: GNU General Public License v3 (GPLv3)
Classifier: Programming Language :: Python
Classifier: Programming Language :: Python :: 3
Classifier: Programming Language :: Python :: 3.9
Classifier: Programming Language :: Python :: 3.10
Classifier: Programming Language :: Python :: 3.11
Classifier: Programming Language :: Python :: 3.12
Classifier: Programming Language :: Python :: 3 :: Only
Classifier: Topic :: Security
Classifier: Typing :: Typed
Requires-Dist: cleo (>=2.1.0,<3.0.0)
Requires-Dist: importlib-metadata (>=4.4) ; python_version < "3.10"
Requires-Dist: platformdirs (>=4.2.2,<5.0.0)
Requires-Dist: typing-extensions (>=4.12.2,<5.0.0)
Project-URL: Bug Tracker, https://github.com/caffeine-addictt/nexis/issues
Project-URL: Documentation, https://github.com/caffeine-addictt/nexis/blob/main/README.md
Project-URL: Homepage, https://github.com/caffeine-addictt/nexis
Project-URL: Release Notes, https://github.com/caffeine-addictt/nexis/releases
Project-URL: Source, https://github.com/caffeine-addictt/nexis
